vigil_client/__init__.py
vigil_client/api.py
vigil_client/auth.py
vigil_client/cli.py
vigil_client/extension.py
vigil_client/models.py
vigil_client/plugins.py
vigil_client/api/__init__.py
vigil_client/api/artifacts.py
vigil_client/api/client.py
vigil_client/api/links.py
vigil_client/api/receipts.py
vigil_client/api/storage.py
vigil_client/api/users.py
vigil_client/cli/__init__.py
vigil_client/cli/__main__.py
vigil_client/cli/artifacts.py
vigil_client/cli/config.py
vigil_client/cli/link.py
vigil_client/cli/login.py
vigil_client/cli/platform_app.py
vigil_client/cli/pull.py
vigil_client/cli/push.py
vigil_client/mcp/__init__.py
vigil_client/mcp/__main__.py
vigil_client/mcp/server.py
vigil_client/mcp/toolspec.yaml
vigil_client/models/__init__.py
vigil_client/models/artifact.py
vigil_client/models/config.py
vigil_client/models/link.py
vigil_client/models/receipt.py
vigil_client/utils/__init__.py
vigil_client/utils/auth.py
vigil_client/utils/config.py
vigil_client/utils/http.py
vigil_client/utils/jwt_validator.py
vigil_client/utils/progress.py
vigil_client/utils/serializer.py
vigil_client-0.3.10.dist-info/METADATA
vigil_client-0.3.10.dist-info/WHEEL
vigil_client-0.3.10.dist-info/entry_points.txt
vigil_client-0.3.10.dist-info/RECORD
